teamhack_ca/__init__.py
teamhack_ca/__main__.py
teamhack_ca/server.py
teamhack_ca-0.0.975.dist-info/LICENSE
teamhack_ca-0.0.975.dist-info/METADATA
teamhack_ca-0.0.975.dist-info/WHEEL
teamhack_ca-0.0.975.dist-info/top_level.txt
teamhack_ca-0.0.975.dist-info/RECORD
