Metadata-Version: 2.1
Name: teamhack-ca
Version: 0.0.975
Summary: Hack the Box Team Support Services
License-File: LICENSE
Requires-Dist: flask-restful
Provides-Extra: rel
Requires-Dist: twine ; extra == 'rel'
Provides-Extra: test
Requires-Dist: coverage ; extra == 'test'
Requires-Dist: pytest ; extra == 'test'
